<?xml version="1.0" encoding="UTF-8"?>
<beans xmlns="http://www.springframework.org/schema/beans"
       xmlns:xsi="http://www.w3.org/2001/XMLSchema-instance"
       xsi:schemaLocation="
http://www.springframework.org/schema/beans http://www.springframework.org/schema/beans/spring-beans-2.0.xsd">
  
  <!-- Interceptor -->
	
  <bean id="statementInterceptor"
    class="org.hisp.dhis.jdbc.statement.StatementInterceptor">
    <property name="statementManager"
    ref="org.hisp.dhis.jdbc.StatementManager"/>
  </bean>
	
  <!-- JDBCConfigurationProvider -->
	
  <bean id="org.hisp.dhis.jdbc.JDBCConfigurationProvider"
    class="org.hisp.dhis.jdbc.configuration.DefaultJDBCConfigurationProvider">
    <property name="configurationProvider"
      ref="org.hisp.dhis.hibernate.HibernateConfigurationProvider"/>	
  </bean>
	
  <!-- StatementManager -->
	
  <bean id="org.hisp.dhis.jdbc.StatementManager"
    class="org.hisp.dhis.jdbc.statement.JDBCStatementManager">
    <property name="configurationProvider"
      ref="org.hisp.dhis.jdbc.JDBCConfigurationProvider"/>
  </bean>
  
  <!-- BatchHandlerFactory -->
	
  <bean id="org.hisp.dhis.jdbc.BatchHandlerFactory"
    class="org.hisp.dhis.jdbc.factory.DefaultBatchHandlerFactory">
    <property name="configurationProvider"
      ref="org.hisp.dhis.jdbc.JDBCConfigurationProvider"/>
  </bean>
  
  <!-- StatementDialect -->

  <bean id="statementDialect" class="org.hisp.dhis.jdbc.statement.StatementDialectFactoryBean">
    <property name="configurationProvider"
      ref="org.hisp.dhis.jdbc.JDBCConfigurationProvider"/>
  </bean>
	
</beans>